lfcrlf/__init__.py
lfcrlf/lfcrlf.py
lf_crlf-0.0.3.dist-info/METADATA
lf_crlf-0.0.3.dist-info/WHEEL
lf_crlf-0.0.3.dist-info/top_level.txt
lf_crlf-0.0.3.dist-info/RECORD
