Metadata-Version: 2.4
Name: lf-crlf
Version: 0.0.3
Summary: A tool to convert line endings between LF and CRLF
Home-page: https://github.com/farfromsouls/LF_CRLF
Author: farfromsouls
Author-email: farfromsouls@gmail.com
Project-URL: GitHub, https://github.com/farfromsouls/LF_CRLF
Project-URL: Bug Reports, https://github.com/farfromsouls/LF_CRLF/issues
Keywords: line endings lf crlf convert text files
Classifier: Programming Language :: Python :: 3.6
Classifier: Programming Language :: Python :: 3.7
Classifier: Programming Language :: Python :: 3.8
Classifier: Programming Language :: Python :: 3.9
Classifier: Programming Language :: Python :: 3.10
Classifier: License :: OSI Approved :: MIT License
Classifier: Operating System :: OS Independent
Classifier: Development Status :: 4 - Beta
Classifier: Intended Audience :: Developers
Classifier: Topic :: Software Development :: Libraries :: Python Modules
Classifier: Topic :: Utilities
Requires-Python: >=3.6
Dynamic: author
Dynamic: author-email
Dynamic: classifier
Dynamic: description
Dynamic: description-content-type
Dynamic: home-page
Dynamic: keywords
Dynamic: project-url
Dynamic: requires-python
Dynamic: summary
